MANIFEST.in
setup.py
data/language_profiles.json
external/gumbo-parser/src/.dirstamp
external/gumbo-parser/src/attribute.c
external/gumbo-parser/src/attribute.h
external/gumbo-parser/src/char_ref.c
external/gumbo-parser/src/char_ref.h
external/gumbo-parser/src/char_ref.rl
external/gumbo-parser/src/error.c
external/gumbo-parser/src/error.h
external/gumbo-parser/src/gumbo.h
external/gumbo-parser/src/insertion_mode.h
external/gumbo-parser/src/parser.c
external/gumbo-parser/src/parser.h
external/gumbo-parser/src/string_buffer.c
external/gumbo-parser/src/string_buffer.h
external/gumbo-parser/src/string_piece.c
external/gumbo-parser/src/string_piece.h
external/gumbo-parser/src/tag.c
external/gumbo-parser/src/tag.in
external/gumbo-parser/src/tag_enum.h
external/gumbo-parser/src/tag_gperf.h
external/gumbo-parser/src/tag_sizes.h
external/gumbo-parser/src/tag_strings.h
external/gumbo-parser/src/token_type.h
external/gumbo-parser/src/tokenizer.c
external/gumbo-parser/src/tokenizer.h
external/gumbo-parser/src/tokenizer_states.h
external/gumbo-parser/src/utf8.c
external/gumbo-parser/src/utf8.h
external/gumbo-parser/src/util.c
external/gumbo-parser/src/util.h
external/gumbo-parser/src/vector.c
external/gumbo-parser/src/vector.h
external/gumbo-parser/src/.deps/.dirstamp
external/gumbo-parser/src/.deps/libgumbo_la-attribute.Plo
external/gumbo-parser/src/.deps/libgumbo_la-char_ref.Plo
external/gumbo-parser/src/.deps/libgumbo_la-error.Plo
external/gumbo-parser/src/.deps/libgumbo_la-parser.Plo
external/gumbo-parser/src/.deps/libgumbo_la-string_buffer.Plo
external/gumbo-parser/src/.deps/libgumbo_la-string_piece.Plo
external/gumbo-parser/src/.deps/libgumbo_la-tag.Plo
external/gumbo-parser/src/.deps/libgumbo_la-tokenizer.Plo
external/gumbo-parser/src/.deps/libgumbo_la-utf8.Plo
external/gumbo-parser/src/.deps/libgumbo_la-util.Plo
external/gumbo-parser/src/.deps/libgumbo_la-vector.Plo
external/json/src/json.hpp
external/json/src/json.hpp.re2c
external/libstemmer/.git
textypy.egg-info/PKG-INFO
textypy.egg-info/SOURCES.txt
textypy.egg-info/dependency_links.txt
textypy.egg-info/top_level.txt
