Metadata-Version: 1.0
Name: textypy
Version: 0.2.0
Summary: python interface for libtexty
Home-page: https://github.com/scivey/libtexty
Author: Scott Ivey
Author-email: scott.ivey@gmail.com
License: UNKNOWN
Platform: UNKNOWN
